{
  "generator-jhipster": {
    "baseName": "matetracker",
    "packageName": "de.atomfrede.matetracker.web",
    "packageFolder": "de/atomfrede/matetracker/web",
    "authenticationType": "oauth2",
    "hibernateCache": "hazelcast",
    "clusteredHttpSession": "hazelcast",
    "websocket": "spring-websocket",
    "databaseType": "sql",
    "devDatabaseType": "h2Memory",
    "prodDatabaseType": "mysql",
    "useCompass": false,
    "buildTool": "gradle",
    "frontendBuilder": "grunt",
    "javaVersion": "8",
    "rememberMeKey": "7670d484940d8831a4da2bb11d0e1e354b7daff1"
  }
}